{
    "基础信息": {
        "名称": {
            "中文名": "茉莉",
            "学名": "Jasminum sambac",
            "别名": [
                "茉莉花",
                "香魂",
                "木梨花"
            ]
        },
        "分类": {
            "科": "木犀科",
            "属": "素馨属",
            "种": "茉莉（Jasminum sambac）"
        }
    },
    "植物学特征": {
        "植株类型": "木本（灌木）",
        "植株形态": {
            "株高": "0.5-3米",
            "冠幅": "1-2米",
            "分枝性": "丛生型"
        },
        "叶片特征": {
            "叶形": [
                "椭圆形",
                "卵形"
            ],
            "叶色": [
                "深绿色"
            ],
            "叶片大小": "3-9 cm",
            "叶序": "对生"
        },
        "花部特征": {
            "花序类型": "聚伞花序/单生",
            "花形": [
                "高脚碟状"
            ],
            "花朵大小": "2-3 cm",
            "花色": [
                "白色"
            ],
            "花期": "5-10月（单朵花开放1-2天）",
            "花香": "浓香，甜香型（类似蜂蜜）"
        },
        "果实与种子": {
            "果实类型": "浆果（栽培中罕见）",
            "种子特征": "黑色小颗粒，自然传播方式不明（人工繁殖以扦插为主）"
        }
    },
    "生长需求": {
        "光照": "全日照（夏季需防强光灼伤）",
        "温度": {
            "耐寒性": "最低5℃",
            "耐热性": "最高35℃",
            "适宜温度": "18-30℃"
        },
        "水分": "喜湿润但忌积水（表土干燥即需浇水）",
        "土壤": {
            "pH值": "中性至微酸性（6.0-7.5）",
            "类型": "疏松肥沃沙质壤土",
            "排水性": "要求良好"
        }
    },
    "栽培管理": {
        "繁殖方式": [
            "扦插",
            "压条"
        ],
        "养护难度": "中等（需精细控水控温）",
        "修剪需求": "花后修剪残花及弱枝（促进二次开花）",
        "特殊处理": [
            "北方冬季需室内保温",
            "花蕾期需避免喷水"
        ],
        "种植间隔": "株距50-80cm",
        "施肥建议": [
            {
                "施肥时期": "生长期（4-9月）",
                "施肥种类": "氮磷钾均衡复合肥",
                "用法": "撒施后覆土",
                "用量": "10-15克/株（每月1次）"
            },
            {
                "施肥时期": "花蕾形成期",
                "施肥种类": "磷酸二氢钾",
                "用法": "叶面喷施",
                "用量": "0.2%溶液（每周1次）"
            }
        ],
        "生长节奏": {
            "萌动信号": "新芽呈嫩绿色",
            "生长旺季": "5-9月",
            "休眠表现": "冬季生长停滞（温度低于10℃时）"
        },
        "缺水信号": "叶片下垂且无晨间恢复（重度缺水时老叶黄化）",
        "肥害表现": "叶缘焦枯（过量施肥导致盐分积累）",
        "常见病虫害": [
            {
                "现象": "白粉病",
                "诱因": [
                    "通风不良",
                    "湿度过高"
                ],
                "鉴别要点": [
                    "叶片表面白色粉状物",
                    "严重时叶片卷曲"
                ],
                "用药": "25%嘧菌酯悬浮剂",
                "用药方式": "喷雾",
                "用药浓度": "1500倍稀释",
                "发病场景": "梅雨季节高发"
            },
            {
                "现象": "红蜘蛛",
                "诱因": [
                    "空气干燥",
                    "通风不畅"
                ],
                "鉴别要点": [
                    "叶背红色虫体",
                    "叶片出现黄白色斑点"
                ],
                "用药": "联苯肼酯悬浮剂",
                "用药方式": "叶背重点喷洒",
                "用药浓度": "3000倍稀释",
                "发病场景": "夏季高温干燥"
            }
        ],
        "抗逆性": [
            "耐修剪",
            "抗污染（对二氧化硫敏感）"
        ],
        "急救方案": {
            "烂根处理": "脱盆去土→剪除腐烂根系→多菌灵浸泡→换新土重栽",
            "冻伤复苏": "移至10℃环境缓苗→逐步升温至15℃"
        }
    },
    "生态与用途": {
        "生态功能": [
            "吸引夜间活动的蛾类传粉",
            "释放负离子"
        ],
        "经济价值": [
            "花茶原料（茉莉花茶）",
            "精油提取（香水工业）"
        ],
        "园林应用": [
            "盆栽",
            "绿篱",
            "庭院丛植"
        ],
        "文化意义": "象征纯洁与永恒爱情（菲律宾国花）"
    },
    "其他信息": {
        "原生地": "印度、阿拉伯半岛",
        "适应区域": "USDA 9-11区",
        "品种差异": [
            "单瓣茉莉：花冠单层，香味最浓",
            "双瓣茉莉：产量高，广泛用于制茶",
            "重瓣茉莉（宝珠茉莉）：花朵球形，观赏性强",
            "虎头茉莉：花瓣层数多达20层，抗性较弱",
            "台湾茉莉：枝条柔软，适合作攀援栽培"
        ],
        "市场信息": [
            "盆栽价格：15-80元（株高30-100cm）",
            "鲜花收购价：40-60元/公斤（盛花期）"
        ]
    },
    "扩展记录": {
        "年度生长日志": "4月萌芽→5月初花→7-8月盛花→11月休眠",
        "抗病记录": "2023年6月白粉病爆发→喷施嘧菌酯后控制",
        "北京地栽养护要点": [
            "10月下旬移入室内（保持夜间不低于8℃）",
            "春季出室前逐步炼苗"
        ],
        "记录提示": [
            "重点关注新梢生长速度与花芽分化关系",
            "记录夜间香气浓度变化（与温度相关性）"
        ]
    }
}